Workbook

Sheet Inputs
A1: AI Automation ROI Calculator
A2: Aiprosol · 2026 · Fill in B-column cells in yellow
A4: VOLUME
A5: Transactions per month (current) | B5: 1000 | C5: Count of items currently processed
A6: Transactions per month (projected with automation) | B6: 1000 | C6: Will it stay the same or grow?
A8: TIME
A9: Average time per transaction — manual (minutes) | B9: 5 | C9: How long currently
A10: Average time per transaction — automated (minutes) | B10: 0.5 | C10: How long after
A11: Working hours per month | B11: 160 | C11: Standard ~160 = 40 × 4 weeks
A13: PEOPLE COSTS
A14: Fully-loaded labour cost per hour (USD) | B14: 50 | C14: Salary × 1.4 typically, ÷ working hours
A15: Number of people doing this work currently | B15: 2 | C15: Headcount touching this process
A17: IMPLEMENTATION COSTS
A18: One-time implementation cost (USD) | B18: 5000 | C18: Build + onboarding
A19: Monthly tool cost (USD) | B19: 50 | C19: n8n + OpenAI + ancillary tools
A20: Monthly maintenance hours | B20: 4 | C20: Hours/month to monitor + fix
A22: CONFIDENCE
A23: Quality vs manual (1=worse, 1.0=same, >1=better) | B23: 1 | C23: Adjust if AI improves quality
A24: Adoption ramp curve — month 1 | B24: 0.3 | C24: Fraction of full benefit in month 1
A25: Adoption ramp curve — month 3 | B25: 0.8 | C25: Fraction of full benefit by month 3
A26: Adoption ramp curve — month 6+ | B26: 1 | C26: Fraction of full benefit at maturity
A27: Risk-adjusted confidence (0-1) | B27: 0.8 | C27: Apply this haircut to projected savings

Sheet Calculations
A1: Auto-computed — do not edit
A3: Hours saved per month at maturity | B3: =Inputs!B7*(Inputs!B10-Inputs!B11)/60
A4: Monthly $ saved at maturity (gross) | B4: =B3*Inputs!B14
A5: Monthly maintenance cost ($) | B5: =Inputs!B22*Inputs!B14
A6: Net monthly savings at maturity ($) | B6: =B4-B5-Inputs!B21
A7: Risk-adjusted net monthly savings ($) | B7: =B6*Inputs!B30
A9: Implementation cost ($) | B9: =Inputs!B20
A10: Payback period at maturity (months) | B10: =IF(B7>0, B9/B7, "N/A")
A12: 12-month gross savings ($) — accounting for ramp | B12: =B7*(Inputs!B27*3 + Inputs!B28*3 + Inputs!B29*6) - B9
A13: 12-month savings at NPV (8% discount) | B13: =B12 / 1.08
A15: ROI multiple over 12 months | B15: =IF(B9>0, B12/B9, "N/A")
A16: Hours/year reclaimed | B16: =B3*12

Sheet 12-Month Projection
A1: 12-Month Cash Flow Projection
A3: Month | B3: Adoption % | C3: Gross $ saved | D3: Maintenance $ | E3: Net $ saved | F3: Cumulative net
A4: 1 | B4: =Inputs!B27 | C4: =B4*Calculations!B4 | D4: =Calculations!B5 | E4: =C4-D4-IF(1=1, Inputs!B20, 0) | F4: =E4
A5: 2 | B5: =Inputs!B27 | C5: =B5*Calculations!B4 | D5: =Calculations!B5 | E5: =C5-D5-IF(2=1, Inputs!B20, 0) | F5: =F4+E5
A6: 3 | B6: =Inputs!B27 | C6: =B6*Calculations!B4 | D6: =Calculations!B5 | E6: =C6-D6-IF(3=1, Inputs!B20, 0) | F6: =F5+E6
A7: 4 | B7: =Inputs!B28 | C7: =B7*Calculations!B4 | D7: =Calculations!B5 | E7: =C7-D7-IF(4=1, Inputs!B20, 0) | F7: =F6+E7
A8: 5 | B8: =Inputs!B28 | C8: =B8*Calculations!B4 | D8: =Calculations!B5 | E8: =C8-D8-IF(5=1, Inputs!B20, 0) | F8: =F7+E8
A9: 6 | B9: =Inputs!B28 | C9: =B9*Calculations!B4 | D9: =Calculations!B5 | E9: =C9-D9-IF(6=1, Inputs!B20, 0) | F9: =F8+E9
A10: 7 | B10: =Inputs!B29 | C10: =B10*Calculations!B4 | D10: =Calculations!B5 | E10: =C10-D10-IF(7=1, Inputs!B20, 0) | F10: =F9+E10
A11: 8 | B11: =Inputs!B29 | C11: =B11*Calculations!B4 | D11: =Calculations!B5 | E11: =C11-D11-IF(8=1, Inputs!B20, 0) | F11: =F10+E11
A12: 9 | B12: =Inputs!B29 | C12: =B12*Calculations!B4 | D12: =Calculations!B5 | E12: =C12-D12-IF(9=1, Inputs!B20, 0) | F12: =F11+E12
A13: 10 | B13: =Inputs!B29 | C13: =B13*Calculations!B4 | D13: =Calculations!B5 | E13: =C13-D13-IF(10=1, Inputs!B20, 0) | F13: =F12+E13
A14: 11 | B14: =Inputs!B29 | C14: =B14*Calculations!B4 | D14: =Calculations!B5 | E14: =C14-D14-IF(11=1, Inputs!B20, 0) | F14: =F13+E14
A15: 12 | B15: =Inputs!B29 | C15: =B15*Calculations!B4 | D15: =Calculations!B5 | E15: =C15-D15-IF(12=1, Inputs!B20, 0) | F15: =F14+E15

Sheet Output (1-page)
A1: ROI Summary
A3: Monthly net savings | B3: =Calculations!B6
A4: Payback period | B4: =Calculations!B10 & " months"
A5: 12-month gross savings | B5: =Calculations!B12
A6: ROI multiple (12mo) | B6: =Calculations!B14 & "x"
A7: Hours reclaimed / year | B7: =Calculations!B15
