Workbook

Sheet Cover
A1: Aiprosol Enterprise AI Readiness Assessment
A3: 120 questions across 12 dimensions
A5: How to use:
A6: 1. On the Scorecard tab, answer each question 0-5 (5 = mature, 0 = absent).
A7: 2. The Summary tab auto-aggregates your score per dimension (0-100).
A8: 3. The Heatmap tab highlights your weakest dimensions in red.
A9: 4. The Action Map tab maps each gap to a 12-month roadmap recommendation.
A10: 5. Re-run quarterly to track maturity progress.
A12: Scoring guide:
A13: 5 — Fully implemented, regularly audited
A14: 4 — Implemented, occasionally audited
A15: 3 — Partial / inconsistent
... A18: 0 — Not on the radar

Sheet Scorecard
A1: Dimension | B1: Question | C1: Score (0-5) | D1: Notes
A2: Data Hygiene | B2: Is customer data deduplicated across systems? | C2: 0
A3: Data Hygiene | B3: Are key entities (customer, account, deal) defined consistently? | C3: 0
A4: Data Hygiene | B4: Is there a single source of truth for each critical entity? | C4: 0
A5: Data Hygiene | B5: Is data freshness monitored (last-modified visibility)? | C5: 0
A6: Data Hygiene | B6: Are PII fields catalogued and access-logged? | C6: 0
A7: Data Hygiene | B7: Are data quality issues tracked in a ticket queue? | C7: 0
A8: Data Hygiene | B8: Is there a defined data steward role? | C8: 0
A9: Data Hygiene | B9: Are schema changes communicated before deployment? | C9: 0
A10: Data Hygiene | B10: Is historical data preserved (vs overwritten) for analysis? | C10: 0
A11: Data Hygiene | B11: Are data warehouses refreshed on a predictable cadence? | C11: 0
A12: Process Documentation | B12: Are top 20 business processes documented in writing? | C12: 0
A13: Process Documentation | B13: Are SOPs reviewed at least annually? | C13: 0
... A121: Strategic Alignment | B121: Is the company telling its AI story externally? | C121: 0

Sheet Summary
A1: Dimension | B1: Score (0-100) | C1: Status
A2: Data Hygiene | B2: =ROUND(AVERAGE(Scorecard!C2:C11)*20, 0) | C2: =IF(B2>=80,"Mature",IF(B2>=60,"Capable",IF(B2>=40,"Emerging","Critical")))
A3: Process Documentation | B3: =ROUND(AVERAGE(Scorecard!C12:C21)*20, 0) | C3: =IF(B3>=80,"Mature",IF(B3>=60,"Capable",IF(B3>=40,"Emerging","Critical")))
A4: Change Management | B4: =ROUND(AVERAGE(Scorecard!C22:C31)*20, 0) | C4: =IF(B4>=80,"Mature",IF(B4>=60,"Capable",IF(B4>=40,"Emerging","Critical")))
A5: Governance | B5: =ROUND(AVERAGE(Scorecard!C32:C41)*20, 0) | C5: =IF(B5>=80,"Mature",IF(B5>=60,"Capable",IF(B5>=40,"Emerging","Critical")))
A6: Integration Debt | B6: =ROUND(AVERAGE(Scorecard!C42:C51)*20, 0) | C6: =IF(B6>=80,"Mature",IF(B6>=60,"Capable",IF(B6>=40,"Emerging","Critical")))
A7: Talent & Skills | B7: =ROUND(AVERAGE(Scorecard!C52:C61)*20, 0) | C7: =IF(B7>=80,"Mature",IF(B7>=60,"Capable",IF(B7>=40,"Emerging","Critical")))
A8: Vendor Strategy | B8: =ROUND(AVERAGE(Scorecard!C62:C71)*20, 0) | C8: =IF(B8>=80,"Mature",IF(B8>=60,"Capable",IF(B8>=40,"Emerging","Critical")))
A9: Security | B9: =ROUND(AVERAGE(Scorecard!C72:C81)*20, 0) | C9: =IF(B9>=80,"Mature",IF(B9>=60,"Capable",IF(B9>=40,"Emerging","Critical")))
A10: Finance Operations | B10: =ROUND(AVERAGE(Scorecard!C82:C91)*20, 0) | C10: =IF(B10>=80,"Mature",IF(B10>=60,"Capable",IF(B10>=40,"Emerging","Critical")))
A11: Customer Operations | B11: =ROUND(AVERAGE(Scorecard!C92:C101)*20, 0) | C11: =IF(B11>=80,"Mature",IF(B11>=60,"Capable",IF(B11>=40,"Emerging","Critical")))
A12: Product Engineering | B12: =ROUND(AVERAGE(Scorecard!C102:C111)*20, 0) | C12: =IF(B12>=80,"Mature",IF(B12>=60,"Capable",IF(B12>=40,"Emerging","Critical")))
A13: Strategic Alignment | B13: =ROUND(AVERAGE(Scorecard!C112:C121)*20, 0) | C13: =IF(B13>=80,"Mature",IF(B13>=60,"Capable",IF(B13>=40,"Emerging","Critical")))
A14: OVERALL | B14: =ROUND(AVERAGE(B2:B13), 0)

Sheet Action Map
A1: Dimension | B1: Score band | C1: Recommended 12-month action
A2: Data Hygiene | B2: Critical (0-39) | C2: Halt new AI initiatives. Run a 90-day foundation sprint: hire a dimension owner, document baseline, ship one quick win.
A3: Data Hygiene | B3: Emerging (40-59) | C3: Pick 1 quick win + 1 structural fix in Q1. Begin quarterly review cadence.
A4: Data Hygiene | B4: Capable (60-79) | C4: Push for differentiation. Identify 2 advanced use cases that compound.
A5: Data Hygiene | B5: Mature (80-100) | C5: Maintain + share patterns externally. Look for opportunities to commercialise expertise.
A6: Process Documentation | B6: Critical (0-39) | C6: Halt new AI initiatives. Run a 90-day foundation sprint: hire a dimension owner, document baseline, ship one quick win.
A7: Process Documentation | B7: Emerging (40-59) | C7: Pick 1 quick win + 1 structural fix in Q1. Begin quarterly review cadence.
A8: Process Documentation | B8: Capable (60-79) | C8: Push for differentiation. Identify 2 advanced use cases that compound.
A9: Process Documentation | B9: Mature (80-100) | C9: Maintain + share patterns externally. Look for opportunities to commercialise expertise.
A10: Change Management | B10: Critical (0-39) | C10: Halt new AI initiatives. Run a 90-day foundation sprint: hire a dimension owner, document baseline, ship one quick win.
A11: Change Management | B11: Emerging (40-59) | C11: Pick 1 quick win + 1 structural fix in Q1. Begin quarterly review cadence.
A12: Change Management | B12: Capable (60-79) | C12: Push for differentiation. Identify 2 advanced use cases that compound.
... A49: Strategic Alignment | B49: Mature (80-100) | C49: Maintain + share patterns externally. Look for opportunities to commercialise expertise.
